{
    "fluentMethods": true,
    "clientRootFolder": "",
    "relationships": [],
    "fields": [
        {
            "fieldName": "title",
            "fieldType": "String",
            "fieldValidateRules": [
                "required",
                "maxlength"
            ],
            "fieldValidateRulesMaxlength": "120"
        },
        {
            "fieldName": "description",
            "fieldType": "String",
            "fieldValidateRules": [
                "required",
                "maxlength"
            ],
            "fieldValidateRulesMaxlength": "2000"
        },
        {
            "fieldName": "fullDay",
            "fieldType": "Boolean"
        },
        {
            "fieldName": "eventStart",
            "fieldType": "ZonedDateTime",
            "fieldValidateRules": [
                "required"
            ]
        },
        {
            "fieldName": "eventEnd",
            "fieldType": "ZonedDateTime",
            "fieldValidateRules": [
                "required"
            ]
        },
        {
            "fieldName": "location",
            "fieldType": "String",
            "fieldValidateRules": [
                "maxlength"
            ],
            "fieldValidateRulesMaxlength": "200"
        },
        {
            "fieldName": "eventImage",
            "fieldType": "byte[]",
            "fieldTypeBlobContent": "image"
        }
    ],
    "changelogDate": "20210111144058",
    "dto": "mapstruct",
    "searchEngine": false,
    "service": "serviceImpl",
    "entityTableName": "my_event",
    "databaseType": "sql",
    "readOnly": false,
    "jpaMetamodelFiltering": true,
    "pagination": "pagination"
}
